LICENSE
registry_factory/__init__.py
registry_factory/checks/__init__.py
registry_factory/checks/accreditation.py
registry_factory/checks/factory_pattern.py
registry_factory/checks/testing.py
registry_factory/checks/versioning.py
registry_factory/factory.py
registry_factory/index.py
registry_factory/patterns/__init__.py
registry_factory/patterns/facade.py
registry_factory/patterns/mediator.py
registry_factory/patterns/metacoding.py
registry_factory/patterns/observer.py
registry_factory/registry.py
registry_factory/tools.py
registry_factory/typescripts.py
registry_factory/utils.py
registry_factory-0.1.3.dist-info/LICENSE
registry_factory-0.1.3.dist-info/METADATA
registry_factory-0.1.3.dist-info/WHEEL
registry_factory-0.1.3.dist-info/RECORD
